README.md
setup.py
skyimages/__init__.py
skyimages/constants.py
skyimages/dataset.py
skyimages/download.py
skyimages/utils.py
skyimages.egg-info/PKG-INFO
skyimages.egg-info/SOURCES.txt
skyimages.egg-info/dependency_links.txt
skyimages.egg-info/requires.txt
skyimages.egg-info/top_level.txt