Metadata-Version: 2.1
Name: skyimages
Version: 0.0.1
Summary: Downloading sky image datasets for pytorch applications
Home-page: https://github.com/FlorianK13/skyimages
Author: Florian Kotthoff
Author-email: flo.pypi@posteo.de
Classifier: Programming Language :: Python :: 3.10
Classifier: Programming Language :: Python :: 3.9
Classifier: Programming Language :: Python :: 3.8
Classifier: Development Status :: 2 - Pre-Alpha
Classifier: Intended Audience :: Science/Research
Requires-Python: >=3.6, <4
Provides-Extra: dev
